apps/__init__.py
apps/ann_search_app.py
apps/nlp_app.py
apps/ocr_app.py
apps/ocr_demo.py
apps_streamlit/__init__.py
apps_streamlit/demo_app.py
examples/__init__.py
examples/demo.py
examples/demo2.py
examples/demo3.py
examples/demo4.py
examples/do.py
examples/fastApiDemo.py
examples/files.py
examples/flask_upload.py
examples/fromScheduler.py
examples/sanic_upload.py
examples/scheduler.py
examples/schedulerr.py
examples/apis/__init__.py
examples/fds/ModelPredictor.py
examples/fds/__init__.py
examples/fds/app_raw.py
examples/fds/app_run.py
examples/fds/hotflag.py
examples/fds/main.py
examples/fds/sklearn_lr_demo.model
examples/fds/sklearn_lr_demo.py
examples/fds/update.py
examples/gunicorn_test/__init__.py
examples/gunicorn_test/flask_app.py
examples/gunicorn_test/gun.py
examples/gunicorn_test/run_gunicorn.py
examples/gunicorn_test/log/18550288233-初级赛题-python.zip
examples/gunicorn_test/log/__init__.py
examples/sanic_/auto_load.py
examples/sanic_/baidu.png
examples/sanic_/download.py
examples/sanic_/log.txt
examples/sanic_/model_train.py
examples/sanic_/model_update.py
examples/sanic_/plus.py
examples/sanic_/upload.py
iapp/App.py
iapp/App_.py
iapp/FlaskApp.py
iapp/SanicApp.py
iapp/__init__.py
iapp/app_run.py
iapp/log/__init__.py
iapp/log/demo.py
iapp/scheduler/Scheduler.py
iapp/scheduler/__init__.py
iapp/scheduler/__sanic.py
iapp/static/__init__.py
iapp/static/css/main.css
iapp/static/js/main.js
iapp/templates/__init__.py
iapp/templates/example_template.html
iapp/templates/index.html
iapp/templates/meeting.html
iapp/templates/upload.html
iapp/utils/Templates.py
iapp/utils/__init__.py
iapp/utils/make_scheduler.py
iapp/utils/upload.py
iapp/webs/__init__.py
iapp/webs/app.py
iapp/webs/jinja_example.py
iapp/webs/meeting.py
iapp-2020.11.5.17.26.13.dist-info/METADATA
iapp-2020.11.5.17.26.13.dist-info/RECORD
iapp-2020.11.5.17.26.13.dist-info/WHEEL
iapp-2020.11.5.17.26.13.dist-info/entry_points.txt
iapp-2020.11.5.17.26.13.dist-info/top_level.txt
