Metadata-Version: 2.1
Name: iapp
Version: 2020.11.5.17.26.13
Summary: description
Home-page: https://github.com/Jie-Yuan/tql-App
Author: JieYuan
Author-email: 313303303@qq.com
Maintainer: JieYuan
Maintainer-email: 313303303@qq.com
License: MIT
Keywords: tool wheel,yuanjie,utils
Platform: all
Classifier: Operating System :: OS Independent
Classifier: Intended Audience :: Developers
Classifier: License :: OSI Approved :: MIT License
Classifier: Programming Language :: Python
Classifier: Programming Language :: Python :: Implementation
Requires-Python: >=3.6
Requires-Dist: fastapi[all]
Requires-Dist: uvicorn
Requires-Dist: fire
